neural_compressor/common/__init__.py
neural_compressor/common/base_config.py
neural_compressor/common/base_tuning.py
neural_compressor/common/tuning_param.py
neural_compressor/common/version.py
neural_compressor/common/utils/__init__.py
neural_compressor/common/utils/constants.py
neural_compressor/common/utils/logger.py
neural_compressor/common/utils/save_load.py
neural_compressor/common/utils/utility.py
neural_compressor/evaluation/__init__.py
neural_compressor/evaluation/bigcode_eval/__init__.py
neural_compressor/evaluation/bigcode_eval/evaluator.py
neural_compressor/evaluation/hf_eval/__init__.py
neural_compressor/evaluation/hf_eval/evaluator.py
neural_compressor/evaluation/hf_eval/hf_datasets/__init__.py
neural_compressor/evaluation/hf_eval/hf_datasets/cnn_dailymail.py
neural_compressor/evaluation/lm_eval/__init__.py
neural_compressor/evaluation/lm_eval/accuracy.py
neural_compressor/evaluation/lm_eval/utils.py
neural_compressor/evaluation/lm_eval/models/__init__.py
neural_compressor/evaluation/lm_eval/models/huggingface.py
neural_compressor/torch/__init__.py
neural_compressor/torch/algorithms/__init__.py
neural_compressor/torch/algorithms/base_algorithm.py
neural_compressor/torch/algorithms/autoround/__init__.py
neural_compressor/torch/algorithms/autoround/autoround.py
neural_compressor/torch/algorithms/fp8_quant/__init__.py
neural_compressor/torch/algorithms/fp8_quant/common.py
neural_compressor/torch/algorithms/fp8_quant/model_configs.py
neural_compressor/torch/algorithms/fp8_quant/observer.py
neural_compressor/torch/algorithms/fp8_quant/patched_module_base.py
neural_compressor/torch/algorithms/fp8_quant/quantizer.py
neural_compressor/torch/algorithms/fp8_quant/save_load.py
neural_compressor/torch/algorithms/fp8_quant/scaling_method_base.py
neural_compressor/torch/algorithms/fp8_quant/_core/__init__.py
neural_compressor/torch/algorithms/fp8_quant/_core/common.py
neural_compressor/torch/algorithms/fp8_quant/_core/external_func_impl.py
neural_compressor_pt-3.7.1.dist-info/LICENSE
neural_compressor_pt-3.7.1.dist-info/METADATA
neural_compressor_pt-3.7.1.dist-info/WHEEL
neural_compressor_pt-3.7.1.dist-info/third-party-programs.txt
neural_compressor_pt-3.7.1.dist-info/top_level.txt
neural_compressor_pt-3.7.1.dist-info/RECORD
